spartacloud/__init__.py
spartacloud/datastore_api.py
spartacloud/datastore_api_cluster.py
spartacloud/spartacloud_api.py
spartacloud/spartacloud_api_utils.py
spartacloud-0.6.dist-info/METADATA
spartacloud-0.6.dist-info/WHEEL
spartacloud-0.6.dist-info/top_level.txt
spartacloud-0.6.dist-info/RECORD
