Metadata-Version: 2.1
Name: spartacloud
Version: 0.6
Summary: Spartacloud Python API
Home-page: https://spartaquant.com
Author: Benjamin Meyer
Author-email: spartacloud@gmail.com
Classifier: Programming Language :: Python :: 3
Classifier: License :: OSI Approved :: MIT License
Classifier: Operating System :: OS Independent
Requires-Python: >=3.6
